{
  "updated": "2026-07-18",
  "spotifyUpdated": true,
  "artist": {
    "name": "Jimin",
    "followers": 12668561,
    "formattedFollowers": "12.7M",
    "monthlyListeners": 5790237,
    "formattedMonthlyListeners": "5.8M"
  },
  "summary": {
    "totalStreams": 14684838276,
    "formattedStreams": "14.68B",
    "totalDailyGain": 2600401,
    "formattedDailyGain": "+2.6M"
  },
  "songs": [
    {
      "title": "Who",
      "streams": 2485369526,
      "trackId": "1yqdD2ScjkqvaNBUzPQ4vR",
      "release": "Who (Remixes)",
      "releaseType": "SINGLE",
      "image": "https://i.scdn.co/image/ab67616d00001e027f35adfbec3bb2bc8256802b",
      "previousStreams": 2484005032,
      "dailyGain": 1364494,
      "yesterdayGain": 1351935,
      "gainDifference": 12559,
      "formattedStreams": "2.49B",
      "formattedDailyGain": "+1.4M",
      "formattedGainDifference": "+12.6K"
    },
    {
      "title": "Who",
      "streams": 2485369526,
      "trackId": "5wPnPIZS8wr4lPNLz4qvHK",
      "release": "MUSE (WONDER ver.)",
      "releaseType": "ALBUM",
      "image": "https://i.scdn.co/image/ab67616d00001e02f150d9f2e5e8148e5032fd7d",
      "previousStreams": 2484005032,
      "dailyGain": 1364494,
      "yesterdayGain": 1351935,
      "gainDifference": 12559,
      "formattedStreams": "2.49B",
      "formattedDailyGain": "+1.4M",
      "formattedGainDifference": "+12.6K"
    },
    {
      "title": "Who",
      "streams": 2485369526,
      "trackId": "32lSgbCqRcIOyUSnfuUZEQ",
      "release": "MUSE (WANDER ver.)",
      "releaseType": "ALBUM",
      "image": "https://i.scdn.co/image/ab67616d00001e0282601539d4a27061ad90eacb",
      "previousStreams": 2484005032,
      "dailyGain": 1364494,
      "yesterdayGain": 1351935,
      "gainDifference": 12559,
      "formattedStreams": "2.49B",
      "formattedDailyGain": "+1.4M",
      "formattedGainDifference": "+12.6K"
    },
    {
      "title": "Who",
      "streams": 2484005032,
      "trackId": "7tI8dRuH2Yc6RuoTjxo4dU",
      "release": "MUSE",
      "releaseType": "ALBUM",
      "image": "https://i.scdn.co/image/ab67616d00001e02f02c451189a709b9a952aaec",
      "previousStreams": 2484005032,
      "dailyGain": 0,
      "yesterdayGain": 1351935,
      "gainDifference": -1351935,
      "formattedStreams": "2.48B",
      "formattedDailyGain": "0",
      "formattedGainDifference": "-1351935"
    },
    {
      "title": "Like Crazy",
      "streams": 1467845149,
      "trackId": "58BWnoFDNaeM0vwA0K3fqb",
      "release": "Like Crazy (Remixes)",
      "releaseType": "EP",
      "image": "https://i.scdn.co/image/ab67616d00001e02f9638e7ed5b7d42e9c514195",
      "previousStreams": 1467624698,
      "dailyGain": 220451,
      "yesterdayGain": 234265,
      "gainDifference": -13814,
      "formattedStreams": "1.47B",
      "formattedDailyGain": "+220.5K",
      "formattedGainDifference": "-13814"
    },
    {
      "title": "Like Crazy",
      "streams": 1467624698,
      "trackId": "3Ua0m0YmEjrMi9XErKcNiR",
      "release": "FACE",
      "releaseType": "EP",
      "image": "https://i.scdn.co/image/ab67616d00001e022b46078245d0120690eb560d",
      "previousStreams": 1467624698,
      "dailyGain": 0,
      "yesterdayGain": 234265,
      "gainDifference": -234265,
      "formattedStreams": "1.47B",
      "formattedDailyGain": "0",
      "formattedGainDifference": "-234265"
    },
    {
      "title": "Set Me Free Pt.2",
      "streams": 480206721,
      "trackId": "1fpj1CJPxY3YvN3AMAEYvt",
      "release": "FACE",
      "releaseType": "EP",
      "image": "https://i.scdn.co/image/ab67616d00001e022b46078245d0120690eb560d",
      "previousStreams": 480206721,
      "dailyGain": 0,
      "yesterdayGain": 134094,
      "gainDifference": -134094,
      "formattedStreams": "480.2M",
      "formattedDailyGain": "0",
      "formattedGainDifference": "-134094"
    },
    {
      "title": "Set Me Free Pt.2",
      "streams": 480206721,
      "trackId": "59hBR0BCtJsfIbV9VzCVAp",
      "release": "Set Me Free Pt.2",
      "releaseType": "SINGLE",
      "image": "https://i.scdn.co/image/ab67616d00001e024f4ec2c2a865569bd4a067a4",
      "previousStreams": 480206721,
      "dailyGain": 0,
      "yesterdayGain": 134094,
      "gainDifference": -134094,
      "formattedStreams": "480.2M",
      "formattedDailyGain": "0",
      "formattedGainDifference": "-134094"
    },
    {
      "title": "Like Crazy (English Version)",
      "streams": 401198395,
      "trackId": "6EY9e6LyPWmL8hUS5E1P0h",
      "release": "Like Crazy (Remixes)",
      "releaseType": "EP",
      "image": "https://i.scdn.co/image/ab67616d00001e02f9638e7ed5b7d42e9c514195",
      "previousStreams": 401144941,
      "dailyGain": 53454,
      "yesterdayGain": 60823,
      "gainDifference": -7369,
      "formattedStreams": "401.2M",
      "formattedDailyGain": "+53.5K",
      "formattedGainDifference": "-7369"
    },
    {
      "title": "Like Crazy (English Version)",
      "streams": 401144941,
      "trackId": "0u8rZGtXJrLtiSe34FPjGG",
      "release": "FACE",
      "releaseType": "EP",
      "image": "https://i.scdn.co/image/ab67616d00001e022b46078245d0120690eb560d",
      "previousStreams": 401144941,
      "dailyGain": 0,
      "yesterdayGain": 60823,
      "gainDifference": -60823,
      "formattedStreams": "401.1M",
      "formattedDailyGain": "0",
      "formattedGainDifference": "-60823"
    },
    {
      "title": "Be Mine",
      "streams": 397004920,
      "trackId": "59ldd5koyBqo1vFp6MusW1",
      "release": "MUSE (WONDER ver.)",
      "releaseType": "ALBUM",
      "image": "https://i.scdn.co/image/ab67616d00001e02f150d9f2e5e8148e5032fd7d",
      "previousStreams": 396748597,
      "dailyGain": 256323,
      "yesterdayGain": 267524,
      "gainDifference": -11201,
      "formattedStreams": "397M",
      "formattedDailyGain": "+256.3K",
      "formattedGainDifference": "-11201"
    },
    {
      "title": "Be Mine",
      "streams": 397004920,
      "trackId": "3VaKWbW68AyOkEl4AxhXA2",
      "release": "MUSE (WANDER ver.)",
      "releaseType": "ALBUM",
      "image": "https://i.scdn.co/image/ab67616d00001e0282601539d4a27061ad90eacb",
      "previousStreams": 396748597,
      "dailyGain": 256323,
      "yesterdayGain": 267524,
      "gainDifference": -11201,
      "formattedStreams": "397M",
      "formattedDailyGain": "+256.3K",
      "formattedGainDifference": "-11201"
    },
    {
      "title": "Be Mine (English Version)",
      "streams": 396748597,
      "trackId": "4DairgmwgyfmFHm0e7kRPL",
      "release": "Be Mine (English Version)",
      "releaseType": "SINGLE",
      "image": "https://i.scdn.co/image/ab67616d00001e0219655636129722b4bd720dbc",
      "previousStreams": 396748597,
      "dailyGain": 0,
      "yesterdayGain": 267524,
      "gainDifference": -267524,
      "formattedStreams": "396.7M",
      "formattedDailyGain": "0",
      "formattedGainDifference": "-267524"
    },
    {
      "title": "Be Mine",
      "streams": 396748597,
      "trackId": "3LWVXp636uLT356Rj08Jaz",
      "release": "MUSE",
      "releaseType": "ALBUM",
      "image": "https://i.scdn.co/image/ab67616d00001e02f02c451189a709b9a952aaec",
      "previousStreams": 396748597,
      "dailyGain": 0,
      "yesterdayGain": 267524,
      "gainDifference": -267524,
      "formattedStreams": "396.7M",
      "formattedDailyGain": "0",
      "formattedGainDifference": "-267524"
    },
    {
      "title": "Closer Than This",
      "streams": 333455036,
      "trackId": "2Zyto2vRT9MEj44Y4qbzcs",
      "release": "MUSE (WONDER ver.)",
      "releaseType": "ALBUM",
      "image": "https://i.scdn.co/image/ab67616d00001e02f150d9f2e5e8148e5032fd7d",
      "previousStreams": 333369081,
      "dailyGain": 85955,
      "yesterdayGain": 92885,
      "gainDifference": -6930,
      "formattedStreams": "333.5M",
      "formattedDailyGain": "+86K",
      "formattedGainDifference": "-6930"
    },
    {
      "title": "Closer Than This",
      "streams": 333455036,
      "trackId": "6OIVG9TFJnqOec4G5rD8pW",
      "release": "MUSE (WANDER ver.)",
      "releaseType": "ALBUM",
      "image": "https://i.scdn.co/image/ab67616d00001e0282601539d4a27061ad90eacb",
      "previousStreams": 333369081,
      "dailyGain": 85955,
      "yesterdayGain": 92885,
      "gainDifference": -6930,
      "formattedStreams": "333.5M",
      "formattedDailyGain": "+86K",
      "formattedGainDifference": "-6930"
    },
    {
      "title": "Closer Than This",
      "streams": 333455036,
      "trackId": "3k6q0O9JnO2GhvD6C8fs20",
      "release": "Closer Than This",
      "releaseType": "SINGLE",
      "image": "https://i.scdn.co/image/ab67616d00001e02e3dbc03f538633dbb40adf37",
      "previousStreams": 333369081,
      "dailyGain": 85955,
      "yesterdayGain": 92885,
      "gainDifference": -6930,
      "formattedStreams": "333.5M",
      "formattedDailyGain": "+86K",
      "formattedGainDifference": "-6930"
    },
    {
      "title": "Closer Than This",
      "streams": 333369081,
      "trackId": "6qafqn8bBMy7t5c5WqpyRk",
      "release": "MUSE",
      "releaseType": "ALBUM",
      "image": "https://i.scdn.co/image/ab67616d00001e02f02c451189a709b9a952aaec",
      "previousStreams": 333369081,
      "dailyGain": 0,
      "yesterdayGain": 92885,
      "gainDifference": -92885,
      "formattedStreams": "333.4M",
      "formattedDailyGain": "0",
      "formattedGainDifference": "-92885"
    },
    {
      "title": "With you",
      "streams": 326258417,
      "trackId": "2gzhQaCTeNgxpeB2TPllyY",
      "release": "Our Blues, Pt. 4 (Original Television Soundtrack)",
      "releaseType": "SINGLE",
      "image": "https://i.scdn.co/image/ab67616d00001e02d90bd8b97e49216c00e55d18",
      "previousStreams": 326217915,
      "dailyGain": 40502,
      "yesterdayGain": 44291,
      "gainDifference": -3789,
      "formattedStreams": "326.3M",
      "formattedDailyGain": "+40.5K",
      "formattedGainDifference": "-3789"
    },
    {
      "title": "VIBE (feat. Jimin of BTS)",
      "streams": 276758704,
      "trackId": "14XLUySagFhP9KoqOTg5ka",
      "release": "VIBE (feat. Jimin of BTS)",
      "releaseType": "SINGLE",
      "image": "https://i.scdn.co/image/ab67616d00001e02278d6cf14513bd97cb580fe7",
      "previousStreams": 276711666,
      "dailyGain": 47038,
      "yesterdayGain": 61310,
      "gainDifference": -14272,
      "formattedStreams": "276.8M",
      "formattedDailyGain": "+47K",
      "formattedGainDifference": "-14272"
    },
    {
      "title": "Smeraldo Garden Marching Band (feat. Loco)",
      "streams": 275372483,
      "trackId": "0KsBlpW6csX9YBVckbTDZh",
      "release": "MUSE (WONDER ver.)",
      "releaseType": "ALBUM",
      "image": "https://i.scdn.co/image/ab67616d00001e02f150d9f2e5e8148e5032fd7d",
      "previousStreams": 275291431,
      "dailyGain": 81052,
      "yesterdayGain": 85444,
      "gainDifference": -4392,
      "formattedStreams": "275.4M",
      "formattedDailyGain": "+81.1K",
      "formattedGainDifference": "-4392"
    },
    {
      "title": "Smeraldo Garden Marching Band (feat. Loco)",
      "streams": 275372483,
      "trackId": "7yODD9DKQIllpZ5eioLZRY",
      "release": "MUSE (WANDER ver.)",
      "releaseType": "ALBUM",
      "image": "https://i.scdn.co/image/ab67616d00001e0282601539d4a27061ad90eacb",
      "previousStreams": 275291431,
      "dailyGain": 81052,
      "yesterdayGain": 85444,
      "gainDifference": -4392,
      "formattedStreams": "275.4M",
      "formattedDailyGain": "+81.1K",
      "formattedGainDifference": "-4392"
    },
    {
      "title": "Smeraldo Garden Marching Band (feat. Loco)",
      "streams": 275372483,
      "trackId": "1kPhV0KQui1phEpjnWIqUN",
      "release": "Smeraldo Garden Marching Band (feat. Loco)",
      "releaseType": "SINGLE",
      "image": "https://i.scdn.co/image/ab67616d00001e0238881a83135ef5b4ace418ba",
      "previousStreams": 275291431,
      "dailyGain": 81052,
      "yesterdayGain": 85444,
      "gainDifference": -4392,
      "formattedStreams": "275.4M",
      "formattedDailyGain": "+81.1K",
      "formattedGainDifference": "-4392"
    },
    {
      "title": "Smeraldo Garden Marching Band (feat. Loco)",
      "streams": 275291431,
      "trackId": "1agDCV4zQqaFwJQNsTgmL1",
      "release": "MUSE",
      "releaseType": "ALBUM",
      "image": "https://i.scdn.co/image/ab67616d00001e02f02c451189a709b9a952aaec",
      "previousStreams": 275291431,
      "dailyGain": 0,
      "yesterdayGain": 85444,
      "gainDifference": -85444,
      "formattedStreams": "275.3M",
      "formattedDailyGain": "0",
      "formattedGainDifference": "-85444"
    },
    {
      "title": "Angel Pt. 1 (feat. Kodak Black, NLE Choppa, Jimin of BTS, JVKE & Muni Long)",
      "streams": 246974291,
      "trackId": "1FEGCMAqh9wzjVM7bPBORE",
      "release": "Angel Anniversary Edition (feat. Muni Long, JVKE, NLE Choppa)",
      "releaseType": "SINGLE",
      "image": "https://i.scdn.co/image/ab67616d00001e0232107dc4737279267c8e00f5",
      "previousStreams": 246943039,
      "dailyGain": 31252,
      "yesterdayGain": 35760,
      "gainDifference": -4508,
      "formattedStreams": "247M",
      "formattedDailyGain": "+31.3K",
      "formattedGainDifference": "-4508"
    },
    {
      "title": "Angel Pt. 1 (feat. Jimin of BTS, JVKE & Muni Long)",
      "streams": 246974291,
      "trackId": "4TZYldxfZlV3hKtZGl8kRb",
      "release": "Angel Pt. 1 (feat. Jimin of BTS, JVKE & Muni Long) (FAST X Soundtrack)",
      "releaseType": "SINGLE",
      "image": "https://i.scdn.co/image/ab67616d00001e02be4afaf12bdbcfd17d95f22b",
      "previousStreams": 246943039,
      "dailyGain": 31252,
      "yesterdayGain": 35760,
      "gainDifference": -4508,
      "formattedStreams": "247M",
      "formattedDailyGain": "+31.3K",
      "formattedGainDifference": "-4508"
    },
    {
      "title": "Angel Pt. 1 (feat. Jimin of BTS, JVKE & Muni Long)",
      "streams": 246974291,
      "trackId": "1vvcEHQdaUTvWt0EIUYcFK",
      "release": "Angel Pt. 1 (feat. Jimin of BTS, JVKE & Muni Long) [Trailer Version]",
      "releaseType": "SINGLE",
      "image": "https://i.scdn.co/image/ab67616d00001e02445afb6341d2685b959251cc",
      "previousStreams": 246943039,
      "dailyGain": 31252,
      "yesterdayGain": 35760,
      "gainDifference": -4508,
      "formattedStreams": "247M",
      "formattedDailyGain": "+31.3K",
      "formattedGainDifference": "-4508"
    },
    {
      "title": "Angel Pt. 1 (feat. Jimin of BTS, JVKE & Muni Long)",
      "streams": 246943039,
      "trackId": "2tC8dLnjkNFMGOqaYMSjcp",
      "release": "Angel Pt. 1 (feat. Jimin of BTS, JVKE & Muni Long) (FAST X Soundtrack)",
      "releaseType": "SINGLE",
      "image": "https://i.scdn.co/image/ab67616d00001e0221ba737cb75af968200cf4bc",
      "previousStreams": 246943039,
      "dailyGain": 0,
      "yesterdayGain": 35760,
      "gainDifference": -35760,
      "formattedStreams": "246.9M",
      "formattedDailyGain": "0",
      "formattedGainDifference": "-35760"
    },
    {
      "title": "Angel Pt. 1 (feat. Jimin of BTS, JVKE & Muni Long)",
      "streams": 246943039,
      "trackId": "4g1Ant3Me43Cm5Lx91bV8e",
      "release": "Angel Pt. 1 (feat. Jimin of BTS, JVKE & Muni Long / FAST X Soundtrack)",
      "releaseType": "SINGLE",
      "image": "https://i.scdn.co/image/ab67616d00001e02beac2a5a6392353b63e5ef15",
      "previousStreams": 246943039,
      "dailyGain": 0,
      "yesterdayGain": 35760,
      "gainDifference": -35760,
      "formattedStreams": "246.9M",
      "formattedDailyGain": "0",
      "formattedGainDifference": "-35760"
    },
    {
      "title": "Face-off",
      "streams": 168354459,
      "trackId": "3OdIiWnYRHPYtC313Z0Bwy",
      "release": "FACE",
      "releaseType": "EP",
      "image": "https://i.scdn.co/image/ab67616d00001e022b46078245d0120690eb560d",
      "previousStreams": 168354459,
      "dailyGain": 0,
      "yesterdayGain": 58478,
      "gainDifference": -58478,
      "formattedStreams": "168.4M",
      "formattedDailyGain": "0",
      "formattedGainDifference": "-58478"
    },
    {
      "title": "Alone",
      "streams": 155368501,
      "trackId": "5Hfnps0jaWFpYg55WOPexG",
      "release": "FACE",
      "releaseType": "EP",
      "image": "https://i.scdn.co/image/ab67616d00001e022b46078245d0120690eb560d",
      "previousStreams": 155368501,
      "dailyGain": 0,
      "yesterdayGain": 41428,
      "gainDifference": -41428,
      "formattedStreams": "155.4M",
      "formattedDailyGain": "0",
      "formattedGainDifference": "-41428"
    },
    {
      "title": "Promise",
      "streams": 149123433,
      "trackId": "2RUcwyW74Sv4VracHFrKdh",
      "release": "Promise",
      "releaseType": "SINGLE",
      "image": "https://i.scdn.co/image/ab67616d00001e0221d21c44fa7a2495c37ce088",
      "previousStreams": 149123433,
      "dailyGain": 0,
      "yesterdayGain": 79491,
      "gainDifference": -79491,
      "formattedStreams": "149.1M",
      "formattedDailyGain": "0",
      "formattedGainDifference": "-79491"
    },
    {
      "title": "Slow Dance (feat. Sofia Carson)",
      "streams": 147855646,
      "trackId": "5XvFNFNsgvmwsWk1T7BfRj",
      "release": "MUSE (WONDER ver.)",
      "releaseType": "ALBUM",
      "image": "https://i.scdn.co/image/ab67616d00001e02f150d9f2e5e8148e5032fd7d",
      "previousStreams": 147781344,
      "dailyGain": 74302,
      "yesterdayGain": 81955,
      "gainDifference": -7653,
      "formattedStreams": "147.9M",
      "formattedDailyGain": "+74.3K",
      "formattedGainDifference": "-7653"
    },
    {
      "title": "Slow Dance (feat. Sofia Carson)",
      "streams": 147855646,
      "trackId": "5nyhz1bxLCiBBIAIcBgiEP",
      "release": "MUSE (WANDER ver.)",
      "releaseType": "ALBUM",
      "image": "https://i.scdn.co/image/ab67616d00001e0282601539d4a27061ad90eacb",
      "previousStreams": 147781344,
      "dailyGain": 74302,
      "yesterdayGain": 81955,
      "gainDifference": -7653,
      "formattedStreams": "147.9M",
      "formattedDailyGain": "+74.3K",
      "formattedGainDifference": "-7653"
    },
    {
      "title": "Slow Dance (feat. Sofia Carson)",
      "streams": 147781344,
      "trackId": "3d2bsbugow8JiNvuaRupFH",
      "release": "MUSE",
      "releaseType": "ALBUM",
      "image": "https://i.scdn.co/image/ab67616d00001e02f02c451189a709b9a952aaec",
      "previousStreams": 147781344,
      "dailyGain": 0,
      "yesterdayGain": 81955,
      "gainDifference": -81955,
      "formattedStreams": "147.8M",
      "formattedDailyGain": "0",
      "formattedGainDifference": "-81955"
    },
    {
      "title": "Rebirth (Intro)",
      "streams": 140354312,
      "trackId": "12YODvwEH9NPutL8OhObfD",
      "release": "MUSE (WONDER ver.)",
      "releaseType": "ALBUM",
      "image": "https://i.scdn.co/image/ab67616d00001e02f150d9f2e5e8148e5032fd7d",
      "previousStreams": 140277693,
      "dailyGain": 76619,
      "yesterdayGain": 75762,
      "gainDifference": 857,
      "formattedStreams": "140.4M",
      "formattedDailyGain": "+76.6K",
      "formattedGainDifference": "+857"
    },
    {
      "title": "Rebirth (Intro)",
      "streams": 140354312,
      "trackId": "1ZtkxrnxZB6r8nIiHwqaUn",
      "release": "MUSE (WANDER ver.)",
      "releaseType": "ALBUM",
      "image": "https://i.scdn.co/image/ab67616d00001e0282601539d4a27061ad90eacb",
      "previousStreams": 140277693,
      "dailyGain": 76619,
      "yesterdayGain": 75762,
      "gainDifference": 857,
      "formattedStreams": "140.4M",
      "formattedDailyGain": "+76.6K",
      "formattedGainDifference": "+857"
    },
    {
      "title": "Rebirth (Intro)",
      "streams": 140277693,
      "trackId": "7gMfVc4zfNIxuMyMGglOHa",
      "release": "MUSE",
      "releaseType": "ALBUM",
      "image": "https://i.scdn.co/image/ab67616d00001e02f02c451189a709b9a952aaec",
      "previousStreams": 140277693,
      "dailyGain": 0,
      "yesterdayGain": 75762,
      "gainDifference": -75762,
      "formattedStreams": "140.3M",
      "formattedDailyGain": "0",
      "formattedGainDifference": "-75762"
    },
    {
      "title": "Angel Pt. 2 (feat. Jimin of BTS & JVKE feat. Charlie Puth & Muni Long)",
      "streams": 132991392,
      "trackId": "3gSobY1JXFJn6wh1ON35ni",
      "release": "Angel Anniversary Edition (feat. Muni Long, JVKE, NLE Choppa)",
      "releaseType": "SINGLE",
      "image": "https://i.scdn.co/image/ab67616d00001e0232107dc4737279267c8e00f5",
      "previousStreams": 132958492,
      "dailyGain": 32900,
      "yesterdayGain": 38457,
      "gainDifference": -5557,
      "formattedStreams": "133M",
      "formattedDailyGain": "+32.9K",
      "formattedGainDifference": "-5557"
    },
    {
      "title": "Angel Pt. 2 (feat. Jimin of BTS, Charlie Puth and Muni Long / FAST X Soundtrack)",
      "streams": 132991392,
      "trackId": "0ApadYqa3GRQkJJ3E7pQDJ",
      "release": "Angel Pt. 2 (feat. Jimin of BTS, Charlie Puth and Muni Long / FAST X Soundtrack)",
      "releaseType": "SINGLE",
      "image": "https://i.scdn.co/image/ab67616d00001e023af4efcbc640cf0cb0888d63",
      "previousStreams": 132958492,
      "dailyGain": 32900,
      "yesterdayGain": 38457,
      "gainDifference": -5557,
      "formattedStreams": "133M",
      "formattedDailyGain": "+32.9K",
      "formattedGainDifference": "-5557"
    },
    {
      "title": "Angel Pt. 2 (feat. Jimin of BTS, Charlie Puth and Muni Long)",
      "streams": 132991392,
      "trackId": "2yjeXq5ahx6UUg2rHaUe6X",
      "release": "Angel Pt. 1 (feat. Jimin of BTS, JVKE & Muni Long) (FAST X Soundtrack)",
      "releaseType": "SINGLE",
      "image": "https://i.scdn.co/image/ab67616d00001e02be4afaf12bdbcfd17d95f22b",
      "previousStreams": 132958492,
      "dailyGain": 32900,
      "yesterdayGain": 38457,
      "gainDifference": -5557,
      "formattedStreams": "133M",
      "formattedDailyGain": "+32.9K",
      "formattedGainDifference": "-5557"
    },
    {
      "title": "Angel Pt. 2",
      "streams": 132958492,
      "trackId": "2q6GfDEbNUwJENX6EZLK4Q",
      "release": "Angel Pt. 2 (Acoustic Version)",
      "releaseType": "SINGLE",
      "image": "https://i.scdn.co/image/ab67616d00001e0279f6a219e637ccf7305d622d",
      "previousStreams": 132958492,
      "dailyGain": 0,
      "yesterdayGain": 38457,
      "gainDifference": -38457,
      "formattedStreams": "133M",
      "formattedDailyGain": "0",
      "formattedGainDifference": "-38457"
    },
    {
      "title": "Angel Pt. 2 (feat. Jimin of BTS, Charlie Puth and Muni Long)",
      "streams": 132958492,
      "trackId": "7lVAWCO7Z6n1bQvLGe2EW3",
      "release": "Angel Pt. 2 (feat. Jimin of BTS, Charlie Puth & Muni Long) (Sped Up) [FAST X Soundtrack]",
      "releaseType": "SINGLE",
      "image": "https://i.scdn.co/image/ab67616d00001e02deaa79daadaf2236d1ac1003",
      "previousStreams": 132958492,
      "dailyGain": 0,
      "yesterdayGain": 38457,
      "gainDifference": -38457,
      "formattedStreams": "133M",
      "formattedDailyGain": "0",
      "formattedGainDifference": "-38457"
    },
    {
      "title": "Angel Pt. 2 (feat. Jimin of BTS, Charlie Puth and Muni Long)",
      "streams": 132958492,
      "trackId": "7miSbL2vUkrkkrRZf1jcmq",
      "release": "Angel Pt. 1 (feat. Jimin of BTS, JVKE & Muni Long) (FAST X Soundtrack)",
      "releaseType": "SINGLE",
      "image": "https://i.scdn.co/image/ab67616d00001e0221ba737cb75af968200cf4bc",
      "previousStreams": 132958492,
      "dailyGain": 0,
      "yesterdayGain": 38457,
      "gainDifference": -38457,
      "formattedStreams": "133M",
      "formattedDailyGain": "0",
      "formattedGainDifference": "-38457"
    },
    {
      "title": "Interlude : Dive",
      "streams": 126630973,
      "trackId": "2qg2jy3v50RwfV5FAqG3a2",
      "release": "FACE",
      "releaseType": "EP",
      "image": "https://i.scdn.co/image/ab67616d00001e022b46078245d0120690eb560d",
      "previousStreams": 126630973,
      "dailyGain": 0,
      "yesterdayGain": 19060,
      "gainDifference": -19060,
      "formattedStreams": "126.6M",
      "formattedDailyGain": "0",
      "formattedGainDifference": "-19060"
    },
    {
      "title": "Interlude : Showtime",
      "streams": 124646855,
      "trackId": "3vKBoDN6DGrxMRDBOe5bQa",
      "release": "MUSE (WONDER ver.)",
      "releaseType": "ALBUM",
      "image": "https://i.scdn.co/image/ab67616d00001e02f150d9f2e5e8148e5032fd7d",
      "previousStreams": 124595563,
      "dailyGain": 51292,
      "yesterdayGain": 55109,
      "gainDifference": -3817,
      "formattedStreams": "124.6M",
      "formattedDailyGain": "+51.3K",
      "formattedGainDifference": "-3817"
    },
    {
      "title": "Interlude : Showtime",
      "streams": 124646855,
      "trackId": "12HctF6VyD118g7eXtWLBo",
      "release": "MUSE (WANDER ver.)",
      "releaseType": "ALBUM",
      "image": "https://i.scdn.co/image/ab67616d00001e0282601539d4a27061ad90eacb",
      "previousStreams": 124595563,
      "dailyGain": 51292,
      "yesterdayGain": 55109,
      "gainDifference": -3817,
      "formattedStreams": "124.6M",
      "formattedDailyGain": "+51.3K",
      "formattedGainDifference": "-3817"
    },
    {
      "title": "Interlude : Showtime",
      "streams": 124595563,
      "trackId": "45zLrK0668WQ5JFMyiYmCS",
      "release": "MUSE",
      "releaseType": "ALBUM",
      "image": "https://i.scdn.co/image/ab67616d00001e02f02c451189a709b9a952aaec",
      "previousStreams": 124595563,
      "dailyGain": 0,
      "yesterdayGain": 55109,
      "gainDifference": -55109,
      "formattedStreams": "124.6M",
      "formattedDailyGain": "0",
      "formattedGainDifference": "-55109"
    },
    {
      "title": "Who (Rock Remix)",
      "streams": 77289983,
      "trackId": "2x9lpe6UIHNqLf8fB8qpb7",
      "release": "Who (Remixes)",
      "releaseType": "SINGLE",
      "image": "https://i.scdn.co/image/ab67616d00001e027f35adfbec3bb2bc8256802b",
      "previousStreams": 77248900,
      "dailyGain": 41083,
      "yesterdayGain": 49791,
      "gainDifference": -8708,
      "formattedStreams": "77.3M",
      "formattedDailyGain": "+41.1K",
      "formattedGainDifference": "-8708"
    },
    {
      "title": "Who (Rock Remix)",
      "streams": 77289983,
      "trackId": "1MC8JLPV4fbvVBqvGSLoDf",
      "release": "MUSE (WONDER ver.)",
      "releaseType": "ALBUM",
      "image": "https://i.scdn.co/image/ab67616d00001e02f150d9f2e5e8148e5032fd7d",
      "previousStreams": 77248900,
      "dailyGain": 41083,
      "yesterdayGain": 49791,
      "gainDifference": -8708,
      "formattedStreams": "77.3M",
      "formattedDailyGain": "+41.1K",
      "formattedGainDifference": "-8708"
    },
    {
      "title": "Who (Acoustic Remix)",
      "streams": 75184510,
      "trackId": "2YKecnWyzkGEDTyNaKBG2H",
      "release": "Who (Remixes)",
      "releaseType": "SINGLE",
      "image": "https://i.scdn.co/image/ab67616d00001e027f35adfbec3bb2bc8256802b",
      "previousStreams": 75146779,
      "dailyGain": 37731,
      "yesterdayGain": 38548,
      "gainDifference": -817,
      "formattedStreams": "75.2M",
      "formattedDailyGain": "+37.7K",
      "formattedGainDifference": "-817"
    },
    {
      "title": "Who (Acoustic Remix)",
      "streams": 75184510,
      "trackId": "10I5rhhFoWZDIN3kEc6Dbo",
      "release": "MUSE (WONDER ver.)",
      "releaseType": "ALBUM",
      "image": "https://i.scdn.co/image/ab67616d00001e02f150d9f2e5e8148e5032fd7d",
      "previousStreams": 75146779,
      "dailyGain": 37731,
      "yesterdayGain": 38548,
      "gainDifference": -817,
      "formattedStreams": "75.2M",
      "formattedDailyGain": "+37.7K",
      "formattedGainDifference": "-817"
    },
    {
      "title": "Who (Shibuyakei Remix)",
      "streams": 61831299,
      "trackId": "1PNdJibg1adHD1pTpYBfGc",
      "release": "Who (Remixes)",
      "releaseType": "SINGLE",
      "image": "https://i.scdn.co/image/ab67616d00001e027f35adfbec3bb2bc8256802b",
      "previousStreams": 61813116,
      "dailyGain": 18183,
      "yesterdayGain": 17868,
      "gainDifference": 315,
      "formattedStreams": "61.8M",
      "formattedDailyGain": "+18.2K",
      "formattedGainDifference": "+315"
    },
    {
      "title": "Who (Shibuyakei Remix)",
      "streams": 61831299,
      "trackId": "1ySWoGgrduSzvtJ3PUzO41",
      "release": "MUSE (WANDER ver.)",
      "releaseType": "ALBUM",
      "image": "https://i.scdn.co/image/ab67616d00001e0282601539d4a27061ad90eacb",
      "previousStreams": 61813116,
      "dailyGain": 18183,
      "yesterdayGain": 17868,
      "gainDifference": 315,
      "formattedStreams": "61.8M",
      "formattedDailyGain": "+18.2K",
      "formattedGainDifference": "+315"
    },
    {
      "title": "Who (Instrumental)",
      "streams": 60757962,
      "trackId": "6t7t37Bex3DV4ADqAwUmwa",
      "release": "Who (Remixes)",
      "releaseType": "SINGLE",
      "image": "https://i.scdn.co/image/ab67616d00001e027f35adfbec3bb2bc8256802b",
      "previousStreams": 60740980,
      "dailyGain": 16982,
      "yesterdayGain": 16303,
      "gainDifference": 679,
      "formattedStreams": "60.8M",
      "formattedDailyGain": "+17K",
      "formattedGainDifference": "+679"
    },
    {
      "title": "Who (Instrumental)",
      "streams": 60757962,
      "trackId": "1Px44tw80Q4rcCl8FxDGOi",
      "release": "MUSE (WONDER ver.)",
      "releaseType": "ALBUM",
      "image": "https://i.scdn.co/image/ab67616d00001e02f150d9f2e5e8148e5032fd7d",
      "previousStreams": 60740980,
      "dailyGain": 16982,
      "yesterdayGain": 16303,
      "gainDifference": 679,
      "formattedStreams": "60.8M",
      "formattedDailyGain": "+17K",
      "formattedGainDifference": "+679"
    },
    {
      "title": "Who (Funky Remix)",
      "streams": 59424455,
      "trackId": "6E9BsGMop0G1jrpQNzugXv",
      "release": "Who (Remixes)",
      "releaseType": "SINGLE",
      "image": "https://i.scdn.co/image/ab67616d00001e027f35adfbec3bb2bc8256802b",
      "previousStreams": 59407564,
      "dailyGain": 16891,
      "yesterdayGain": 16589,
      "gainDifference": 302,
      "formattedStreams": "59.4M",
      "formattedDailyGain": "+16.9K",
      "formattedGainDifference": "+302"
    },
    {
      "title": "Who (Funky Remix)",
      "streams": 59424455,
      "trackId": "7KZNgri6Jxw88FAfATw6i9",
      "release": "MUSE (WANDER ver.)",
      "releaseType": "ALBUM",
      "image": "https://i.scdn.co/image/ab67616d00001e0282601539d4a27061ad90eacb",
      "previousStreams": 59407564,
      "dailyGain": 16891,
      "yesterdayGain": 16589,
      "gainDifference": 302,
      "formattedStreams": "59.4M",
      "formattedDailyGain": "+16.9K",
      "formattedGainDifference": "+302"
    },
    {
      "title": "Who (Beautiful Mind Remix)",
      "streams": 59161329,
      "trackId": "1GDjQlek7EFZ3qTyySTSAF",
      "release": "Who (Remixes)",
      "releaseType": "SINGLE",
      "image": "https://i.scdn.co/image/ab67616d00001e027f35adfbec3bb2bc8256802b",
      "previousStreams": 59144012,
      "dailyGain": 17317,
      "yesterdayGain": 16166,
      "gainDifference": 1151,
      "formattedStreams": "59.2M",
      "formattedDailyGain": "+17.3K",
      "formattedGainDifference": "+1.2K"
    },
    {
      "title": "Who (Beautiful Mind Remix)",
      "streams": 59161329,
      "trackId": "2isRbZIIU4PqPrECffn7QO",
      "release": "MUSE (WANDER ver.)",
      "releaseType": "ALBUM",
      "image": "https://i.scdn.co/image/ab67616d00001e0282601539d4a27061ad90eacb",
      "previousStreams": 59144012,
      "dailyGain": 17317,
      "yesterdayGain": 16166,
      "gainDifference": 1151,
      "formattedStreams": "59.2M",
      "formattedDailyGain": "+17.3K",
      "formattedGainDifference": "+1.2K"
    },
    {
      "title": "Angel Pt. 1 (feat. Jimin of BTS, JVKE & Muni Long) - Trailer Version",
      "streams": 55008156,
      "trackId": "2GhOHZynysGm5B8R6iCihi",
      "release": "Angel Pt. 1 (feat. Jimin of BTS, JVKE & Muni Long) [Trailer Version]",
      "releaseType": "SINGLE",
      "image": "https://i.scdn.co/image/ab67616d00001e02445afb6341d2685b959251cc",
      "previousStreams": 55001323,
      "dailyGain": 6833,
      "yesterdayGain": 8549,
      "gainDifference": -1716,
      "formattedStreams": "55M",
      "formattedDailyGain": "+6.8K",
      "formattedGainDifference": "-1716"
    },
    {
      "title": "Angel Pt. 1 (feat. Jimin of BTS, JVKE & Muni Long) - Trailer Version",
      "streams": 55008156,
      "trackId": "5qyjy0xfsHNzWxvXkHVB85",
      "release": "Angel Pt. 1 (feat. Jimin of BTS, JVKE & Muni Long) [Trailer Version]",
      "releaseType": "SINGLE",
      "image": "https://i.scdn.co/image/ab67616d00001e02146ea147ce8c185e71b3b84e",
      "previousStreams": 55001323,
      "dailyGain": 6833,
      "yesterdayGain": 8549,
      "gainDifference": -1716,
      "formattedStreams": "55M",
      "formattedDailyGain": "+6.8K",
      "formattedGainDifference": "-1716"
    },
    {
      "title": "Angel Pt. 1 (feat. Jimin of BTS, JVKE & Muni Long) - Trailer Version",
      "streams": 55001323,
      "trackId": "2rgCR1PPHPGJBppdBOqor0",
      "release": "Angel Pt. 1 (feat. Jimin of BTS, JVKE & Muni Long) (FAST X Soundtrack)",
      "releaseType": "SINGLE",
      "image": "https://i.scdn.co/image/ab67616d00001e0221ba737cb75af968200cf4bc",
      "previousStreams": 55001323,
      "dailyGain": 0,
      "yesterdayGain": 8549,
      "gainDifference": -8549,
      "formattedStreams": "55M",
      "formattedDailyGain": "0",
      "formattedGainDifference": "-8549"
    },
    {
      "title": "Christmas Love",
      "streams": 49728144,
      "trackId": "5oaQsszgxYAdABuXoWEOUe",
      "release": "Christmas Love",
      "releaseType": "SINGLE",
      "image": "https://i.scdn.co/image/ab67616d00001e026102fbfee73db153a32d02ab",
      "previousStreams": 49716945,
      "dailyGain": 11199,
      "yesterdayGain": 12018,
      "gainDifference": -819,
      "formattedStreams": "49.7M",
      "formattedDailyGain": "+11.2K",
      "formattedGainDifference": "-819"
    },
    {
      "title": "Like Crazy (Deep House Remix)",
      "streams": 37578214,
      "trackId": "6D90VTeGEWYX5AkAtjHZh1",
      "release": "Like Crazy (Remixes)",
      "releaseType": "EP",
      "image": "https://i.scdn.co/image/ab67616d00001e02f9638e7ed5b7d42e9c514195",
      "previousStreams": 37572502,
      "dailyGain": 5712,
      "yesterdayGain": 6479,
      "gainDifference": -767,
      "formattedStreams": "37.6M",
      "formattedDailyGain": "+5.7K",
      "formattedGainDifference": "-767"
    },
    {
      "title": "Like Crazy (UK Garage Remix)",
      "streams": 35749684,
      "trackId": "5tDxLjAnkojfnXnjOk6mvh",
      "release": "Like Crazy (Remixes)",
      "releaseType": "EP",
      "image": "https://i.scdn.co/image/ab67616d00001e02f9638e7ed5b7d42e9c514195",
      "previousStreams": 35744572,
      "dailyGain": 5112,
      "yesterdayGain": 5756,
      "gainDifference": -644,
      "formattedStreams": "35.7M",
      "formattedDailyGain": "+5.1K",
      "formattedGainDifference": "-644"
    },
    {
      "title": "Like Crazy (Instrumental)",
      "streams": 26294972,
      "trackId": "0cxhv3PpIkmREXqobuB0zG",
      "release": "Like Crazy (Remixes)",
      "releaseType": "EP",
      "image": "https://i.scdn.co/image/ab67616d00001e02f9638e7ed5b7d42e9c514195",
      "previousStreams": 26290374,
      "dailyGain": 4598,
      "yesterdayGain": 5206,
      "gainDifference": -608,
      "formattedStreams": "26.3M",
      "formattedDailyGain": "+4.6K",
      "formattedGainDifference": "-608"
    },
    {
      "title": "With you - Instrumental",
      "streams": 21887806,
      "trackId": "7M30L99pePlQ3wh8IxVUsD",
      "release": "Our Blues, Pt. 4 (Original Television Soundtrack)",
      "releaseType": "SINGLE",
      "image": "https://i.scdn.co/image/ab67616d00001e02d90bd8b97e49216c00e55d18",
      "previousStreams": 21886688,
      "dailyGain": 1118,
      "yesterdayGain": 1535,
      "gainDifference": -417,
      "formattedStreams": "21.9M",
      "formattedDailyGain": "+1.1K",
      "formattedGainDifference": "-417"
    },
    {
      "title": "Angel Pt. 2 - Acoustic Version",
      "streams": 8059597,
      "trackId": "46rplB2GaD79JaBn94qfqi",
      "release": "Angel Pt. 2 (Acoustic Version)",
      "releaseType": "SINGLE",
      "image": "https://i.scdn.co/image/ab67616d00001e0279f6a219e637ccf7305d622d",
      "previousStreams": 8059597,
      "dailyGain": 0,
      "yesterdayGain": 3014,
      "gainDifference": -3014,
      "formattedStreams": "8.1M",
      "formattedDailyGain": "0",
      "formattedGainDifference": "-3014"
    },
    {
      "title": "Angel (feat. Muni Long, JVKE, NLE Choppa) (Anniversary Edition)",
      "streams": 5609913,
      "trackId": "2PMEMxJCxOz0RGT0mQXXZq",
      "release": "Angel Anniversary Edition (feat. Muni Long, JVKE, NLE Choppa)",
      "releaseType": "SINGLE",
      "image": "https://i.scdn.co/image/ab67616d00001e0232107dc4737279267c8e00f5",
      "previousStreams": 5607905,
      "dailyGain": 2008,
      "yesterdayGain": 3157,
      "gainDifference": -1149,
      "formattedStreams": "5.6M",
      "formattedDailyGain": "+2K",
      "formattedGainDifference": "-1149"
    },
    {
      "title": "Angel (feat. Muni Long, JVKE, NLE Choppa) (Anniversary Edition)",
      "streams": 5607905,
      "trackId": "1XE3rehhUySx3O1fALkswV",
      "release": "Angel Anniversary Edition (feat. Muni Long, JVKE, NLE Choppa)",
      "releaseType": "SINGLE",
      "image": "https://i.scdn.co/image/ab67616d00001e025cae2e3d2932cd9283cc53ff",
      "previousStreams": 5607905,
      "dailyGain": 0,
      "yesterdayGain": 3157,
      "gainDifference": -3157,
      "formattedStreams": "5.6M",
      "formattedDailyGain": "0",
      "formattedGainDifference": "-3157"
    },
    {
      "title": "Angel Pt. 2 - Sped Up",
      "streams": 4153900,
      "trackId": "6aB2aRNg9gTj6XMQkW0yQk",
      "release": "Angel Pt. 2 (Acoustic Version)",
      "releaseType": "SINGLE",
      "image": "https://i.scdn.co/image/ab67616d00001e0279f6a219e637ccf7305d622d",
      "previousStreams": 4153900,
      "dailyGain": 0,
      "yesterdayGain": 2282,
      "gainDifference": -2282,
      "formattedStreams": "4.2M",
      "formattedDailyGain": "0",
      "formattedGainDifference": "-2282"
    },
    {
      "title": "Angel Pt. 2 (feat. Jimin of BTS, Charlie Puth & Muni Long) (Sped Up)",
      "streams": 4153900,
      "trackId": "4rrGx1CX8RwQMl2ufnQzUA",
      "release": "Angel Pt. 2 (feat. Jimin of BTS, Charlie Puth & Muni Long) (Sped Up) [FAST X Soundtrack]",
      "releaseType": "SINGLE",
      "image": "https://i.scdn.co/image/ab67616d00001e02deaa79daadaf2236d1ac1003",
      "previousStreams": 4153900,
      "dailyGain": 0,
      "yesterdayGain": 2282,
      "gainDifference": -2282,
      "formattedStreams": "4.2M",
      "formattedDailyGain": "0",
      "formattedGainDifference": "-2282"
    }
  ],
  "releases": [
    {
      "title": "MUSE (WONDER ver.)",
      "type": "ALBUM",
      "image": "https://i.scdn.co/image/ab67616d00001e02f150d9f2e5e8148e5032fd7d",
      "streams": 4117291233,
      "dailyGain": 2085833,
      "songs": [
        {
          "title": "Who",
          "streams": 2485369526,
          "trackId": "5wPnPIZS8wr4lPNLz4qvHK",
          "release": "MUSE (WONDER ver.)",
          "releaseType": "ALBUM",
          "image": "https://i.scdn.co/image/ab67616d00001e02f150d9f2e5e8148e5032fd7d",
          "previousStreams": 2484005032,
          "dailyGain": 1364494,
          "yesterdayGain": 1351935,
          "gainDifference": 12559,
          "formattedStreams": "2.49B",
          "formattedDailyGain": "+1.4M",
          "formattedGainDifference": "+12.6K"
        },
        {
          "title": "Be Mine",
          "streams": 397004920,
          "trackId": "59ldd5koyBqo1vFp6MusW1",
          "release": "MUSE (WONDER ver.)",
          "releaseType": "ALBUM",
          "image": "https://i.scdn.co/image/ab67616d00001e02f150d9f2e5e8148e5032fd7d",
          "previousStreams": 396748597,
          "dailyGain": 256323,
          "yesterdayGain": 267524,
          "gainDifference": -11201,
          "formattedStreams": "397M",
          "formattedDailyGain": "+256.3K",
          "formattedGainDifference": "-11201"
        },
        {
          "title": "Closer Than This",
          "streams": 333455036,
          "trackId": "2Zyto2vRT9MEj44Y4qbzcs",
          "release": "MUSE (WONDER ver.)",
          "releaseType": "ALBUM",
          "image": "https://i.scdn.co/image/ab67616d00001e02f150d9f2e5e8148e5032fd7d",
          "previousStreams": 333369081,
          "dailyGain": 85955,
          "yesterdayGain": 92885,
          "gainDifference": -6930,
          "formattedStreams": "333.5M",
          "formattedDailyGain": "+86K",
          "formattedGainDifference": "-6930"
        },
        {
          "title": "Smeraldo Garden Marching Band (feat. Loco)",
          "streams": 275372483,
          "trackId": "0KsBlpW6csX9YBVckbTDZh",
          "release": "MUSE (WONDER ver.)",
          "releaseType": "ALBUM",
          "image": "https://i.scdn.co/image/ab67616d00001e02f150d9f2e5e8148e5032fd7d",
          "previousStreams": 275291431,
          "dailyGain": 81052,
          "yesterdayGain": 85444,
          "gainDifference": -4392,
          "formattedStreams": "275.4M",
          "formattedDailyGain": "+81.1K",
          "formattedGainDifference": "-4392"
        },
        {
          "title": "Slow Dance (feat. Sofia Carson)",
          "streams": 147855646,
          "trackId": "5XvFNFNsgvmwsWk1T7BfRj",
          "release": "MUSE (WONDER ver.)",
          "releaseType": "ALBUM",
          "image": "https://i.scdn.co/image/ab67616d00001e02f150d9f2e5e8148e5032fd7d",
          "previousStreams": 147781344,
          "dailyGain": 74302,
          "yesterdayGain": 81955,
          "gainDifference": -7653,
          "formattedStreams": "147.9M",
          "formattedDailyGain": "+74.3K",
          "formattedGainDifference": "-7653"
        },
        {
          "title": "Rebirth (Intro)",
          "streams": 140354312,
          "trackId": "12YODvwEH9NPutL8OhObfD",
          "release": "MUSE (WONDER ver.)",
          "releaseType": "ALBUM",
          "image": "https://i.scdn.co/image/ab67616d00001e02f150d9f2e5e8148e5032fd7d",
          "previousStreams": 140277693,
          "dailyGain": 76619,
          "yesterdayGain": 75762,
          "gainDifference": 857,
          "formattedStreams": "140.4M",
          "formattedDailyGain": "+76.6K",
          "formattedGainDifference": "+857"
        },
        {
          "title": "Interlude : Showtime",
          "streams": 124646855,
          "trackId": "3vKBoDN6DGrxMRDBOe5bQa",
          "release": "MUSE (WONDER ver.)",
          "releaseType": "ALBUM",
          "image": "https://i.scdn.co/image/ab67616d00001e02f150d9f2e5e8148e5032fd7d",
          "previousStreams": 124595563,
          "dailyGain": 51292,
          "yesterdayGain": 55109,
          "gainDifference": -3817,
          "formattedStreams": "124.6M",
          "formattedDailyGain": "+51.3K",
          "formattedGainDifference": "-3817"
        },
        {
          "title": "Who (Rock Remix)",
          "streams": 77289983,
          "trackId": "1MC8JLPV4fbvVBqvGSLoDf",
          "release": "MUSE (WONDER ver.)",
          "releaseType": "ALBUM",
          "image": "https://i.scdn.co/image/ab67616d00001e02f150d9f2e5e8148e5032fd7d",
          "previousStreams": 77248900,
          "dailyGain": 41083,
          "yesterdayGain": 49791,
          "gainDifference": -8708,
          "formattedStreams": "77.3M",
          "formattedDailyGain": "+41.1K",
          "formattedGainDifference": "-8708"
        },
        {
          "title": "Who (Acoustic Remix)",
          "streams": 75184510,
          "trackId": "10I5rhhFoWZDIN3kEc6Dbo",
          "release": "MUSE (WONDER ver.)",
          "releaseType": "ALBUM",
          "image": "https://i.scdn.co/image/ab67616d00001e02f150d9f2e5e8148e5032fd7d",
          "previousStreams": 75146779,
          "dailyGain": 37731,
          "yesterdayGain": 38548,
          "gainDifference": -817,
          "formattedStreams": "75.2M",
          "formattedDailyGain": "+37.7K",
          "formattedGainDifference": "-817"
        },
        {
          "title": "Who (Instrumental)",
          "streams": 60757962,
          "trackId": "1Px44tw80Q4rcCl8FxDGOi",
          "release": "MUSE (WONDER ver.)",
          "releaseType": "ALBUM",
          "image": "https://i.scdn.co/image/ab67616d00001e02f150d9f2e5e8148e5032fd7d",
          "previousStreams": 60740980,
          "dailyGain": 16982,
          "yesterdayGain": 16303,
          "gainDifference": 679,
          "formattedStreams": "60.8M",
          "formattedDailyGain": "+17K",
          "formattedGainDifference": "+679"
        }
      ]
    },
    {
      "title": "MUSE (WANDER ver.)",
      "type": "ALBUM",
      "image": "https://i.scdn.co/image/ab67616d00001e0282601539d4a27061ad90eacb",
      "streams": 4084475861,
      "dailyGain": 2042428,
      "songs": [
        {
          "title": "Who",
          "streams": 2485369526,
          "trackId": "32lSgbCqRcIOyUSnfuUZEQ",
          "release": "MUSE (WANDER ver.)",
          "releaseType": "ALBUM",
          "image": "https://i.scdn.co/image/ab67616d00001e0282601539d4a27061ad90eacb",
          "previousStreams": 2484005032,
          "dailyGain": 1364494,
          "yesterdayGain": 1351935,
          "gainDifference": 12559,
          "formattedStreams": "2.49B",
          "formattedDailyGain": "+1.4M",
          "formattedGainDifference": "+12.6K"
        },
        {
          "title": "Be Mine",
          "streams": 397004920,
          "trackId": "3VaKWbW68AyOkEl4AxhXA2",
          "release": "MUSE (WANDER ver.)",
          "releaseType": "ALBUM",
          "image": "https://i.scdn.co/image/ab67616d00001e0282601539d4a27061ad90eacb",
          "previousStreams": 396748597,
          "dailyGain": 256323,
          "yesterdayGain": 267524,
          "gainDifference": -11201,
          "formattedStreams": "397M",
          "formattedDailyGain": "+256.3K",
          "formattedGainDifference": "-11201"
        },
        {
          "title": "Closer Than This",
          "streams": 333455036,
          "trackId": "6OIVG9TFJnqOec4G5rD8pW",
          "release": "MUSE (WANDER ver.)",
          "releaseType": "ALBUM",
          "image": "https://i.scdn.co/image/ab67616d00001e0282601539d4a27061ad90eacb",
          "previousStreams": 333369081,
          "dailyGain": 85955,
          "yesterdayGain": 92885,
          "gainDifference": -6930,
          "formattedStreams": "333.5M",
          "formattedDailyGain": "+86K",
          "formattedGainDifference": "-6930"
        },
        {
          "title": "Smeraldo Garden Marching Band (feat. Loco)",
          "streams": 275372483,
          "trackId": "7yODD9DKQIllpZ5eioLZRY",
          "release": "MUSE (WANDER ver.)",
          "releaseType": "ALBUM",
          "image": "https://i.scdn.co/image/ab67616d00001e0282601539d4a27061ad90eacb",
          "previousStreams": 275291431,
          "dailyGain": 81052,
          "yesterdayGain": 85444,
          "gainDifference": -4392,
          "formattedStreams": "275.4M",
          "formattedDailyGain": "+81.1K",
          "formattedGainDifference": "-4392"
        },
        {
          "title": "Slow Dance (feat. Sofia Carson)",
          "streams": 147855646,
          "trackId": "5nyhz1bxLCiBBIAIcBgiEP",
          "release": "MUSE (WANDER ver.)",
          "releaseType": "ALBUM",
          "image": "https://i.scdn.co/image/ab67616d00001e0282601539d4a27061ad90eacb",
          "previousStreams": 147781344,
          "dailyGain": 74302,
          "yesterdayGain": 81955,
          "gainDifference": -7653,
          "formattedStreams": "147.9M",
          "formattedDailyGain": "+74.3K",
          "formattedGainDifference": "-7653"
        },
        {
          "title": "Rebirth (Intro)",
          "streams": 140354312,
          "trackId": "1ZtkxrnxZB6r8nIiHwqaUn",
          "release": "MUSE (WANDER ver.)",
          "releaseType": "ALBUM",
          "image": "https://i.scdn.co/image/ab67616d00001e0282601539d4a27061ad90eacb",
          "previousStreams": 140277693,
          "dailyGain": 76619,
          "yesterdayGain": 75762,
          "gainDifference": 857,
          "formattedStreams": "140.4M",
          "formattedDailyGain": "+76.6K",
          "formattedGainDifference": "+857"
        },
        {
          "title": "Interlude : Showtime",
          "streams": 124646855,
          "trackId": "12HctF6VyD118g7eXtWLBo",
          "release": "MUSE (WANDER ver.)",
          "releaseType": "ALBUM",
          "image": "https://i.scdn.co/image/ab67616d00001e0282601539d4a27061ad90eacb",
          "previousStreams": 124595563,
          "dailyGain": 51292,
          "yesterdayGain": 55109,
          "gainDifference": -3817,
          "formattedStreams": "124.6M",
          "formattedDailyGain": "+51.3K",
          "formattedGainDifference": "-3817"
        },
        {
          "title": "Who (Shibuyakei Remix)",
          "streams": 61831299,
          "trackId": "1ySWoGgrduSzvtJ3PUzO41",
          "release": "MUSE (WANDER ver.)",
          "releaseType": "ALBUM",
          "image": "https://i.scdn.co/image/ab67616d00001e0282601539d4a27061ad90eacb",
          "previousStreams": 61813116,
          "dailyGain": 18183,
          "yesterdayGain": 17868,
          "gainDifference": 315,
          "formattedStreams": "61.8M",
          "formattedDailyGain": "+18.2K",
          "formattedGainDifference": "+315"
        },
        {
          "title": "Who (Funky Remix)",
          "streams": 59424455,
          "trackId": "7KZNgri6Jxw88FAfATw6i9",
          "release": "MUSE (WANDER ver.)",
          "releaseType": "ALBUM",
          "image": "https://i.scdn.co/image/ab67616d00001e0282601539d4a27061ad90eacb",
          "previousStreams": 59407564,
          "dailyGain": 16891,
          "yesterdayGain": 16589,
          "gainDifference": 302,
          "formattedStreams": "59.4M",
          "formattedDailyGain": "+16.9K",
          "formattedGainDifference": "+302"
        },
        {
          "title": "Who (Beautiful Mind Remix)",
          "streams": 59161329,
          "trackId": "2isRbZIIU4PqPrECffn7QO",
          "release": "MUSE (WANDER ver.)",
          "releaseType": "ALBUM",
          "image": "https://i.scdn.co/image/ab67616d00001e0282601539d4a27061ad90eacb",
          "previousStreams": 59144012,
          "dailyGain": 17317,
          "yesterdayGain": 16166,
          "gainDifference": 1151,
          "formattedStreams": "59.2M",
          "formattedDailyGain": "+17.3K",
          "formattedGainDifference": "+1.2K"
        }
      ]
    },
    {
      "title": "MUSE",
      "type": "ALBUM",
      "image": "https://i.scdn.co/image/ab67616d00001e02f02c451189a709b9a952aaec",
      "streams": 3902068741,
      "dailyGain": 0,
      "songs": [
        {
          "title": "Who",
          "streams": 2484005032,
          "trackId": "7tI8dRuH2Yc6RuoTjxo4dU",
          "release": "MUSE",
          "releaseType": "ALBUM",
          "image": "https://i.scdn.co/image/ab67616d00001e02f02c451189a709b9a952aaec",
          "previousStreams": 2484005032,
          "dailyGain": 0,
          "yesterdayGain": 1351935,
          "gainDifference": -1351935,
          "formattedStreams": "2.48B",
          "formattedDailyGain": "0",
          "formattedGainDifference": "-1351935"
        },
        {
          "title": "Be Mine",
          "streams": 396748597,
          "trackId": "3LWVXp636uLT356Rj08Jaz",
          "release": "MUSE",
          "releaseType": "ALBUM",
          "image": "https://i.scdn.co/image/ab67616d00001e02f02c451189a709b9a952aaec",
          "previousStreams": 396748597,
          "dailyGain": 0,
          "yesterdayGain": 267524,
          "gainDifference": -267524,
          "formattedStreams": "396.7M",
          "formattedDailyGain": "0",
          "formattedGainDifference": "-267524"
        },
        {
          "title": "Closer Than This",
          "streams": 333369081,
          "trackId": "6qafqn8bBMy7t5c5WqpyRk",
          "release": "MUSE",
          "releaseType": "ALBUM",
          "image": "https://i.scdn.co/image/ab67616d00001e02f02c451189a709b9a952aaec",
          "previousStreams": 333369081,
          "dailyGain": 0,
          "yesterdayGain": 92885,
          "gainDifference": -92885,
          "formattedStreams": "333.4M",
          "formattedDailyGain": "0",
          "formattedGainDifference": "-92885"
        },
        {
          "title": "Smeraldo Garden Marching Band (feat. Loco)",
          "streams": 275291431,
          "trackId": "1agDCV4zQqaFwJQNsTgmL1",
          "release": "MUSE",
          "releaseType": "ALBUM",
          "image": "https://i.scdn.co/image/ab67616d00001e02f02c451189a709b9a952aaec",
          "previousStreams": 275291431,
          "dailyGain": 0,
          "yesterdayGain": 85444,
          "gainDifference": -85444,
          "formattedStreams": "275.3M",
          "formattedDailyGain": "0",
          "formattedGainDifference": "-85444"
        },
        {
          "title": "Slow Dance (feat. Sofia Carson)",
          "streams": 147781344,
          "trackId": "3d2bsbugow8JiNvuaRupFH",
          "release": "MUSE",
          "releaseType": "ALBUM",
          "image": "https://i.scdn.co/image/ab67616d00001e02f02c451189a709b9a952aaec",
          "previousStreams": 147781344,
          "dailyGain": 0,
          "yesterdayGain": 81955,
          "gainDifference": -81955,
          "formattedStreams": "147.8M",
          "formattedDailyGain": "0",
          "formattedGainDifference": "-81955"
        },
        {
          "title": "Rebirth (Intro)",
          "streams": 140277693,
          "trackId": "7gMfVc4zfNIxuMyMGglOHa",
          "release": "MUSE",
          "releaseType": "ALBUM",
          "image": "https://i.scdn.co/image/ab67616d00001e02f02c451189a709b9a952aaec",
          "previousStreams": 140277693,
          "dailyGain": 0,
          "yesterdayGain": 75762,
          "gainDifference": -75762,
          "formattedStreams": "140.3M",
          "formattedDailyGain": "0",
          "formattedGainDifference": "-75762"
        },
        {
          "title": "Interlude : Showtime",
          "streams": 124595563,
          "trackId": "45zLrK0668WQ5JFMyiYmCS",
          "release": "MUSE",
          "releaseType": "ALBUM",
          "image": "https://i.scdn.co/image/ab67616d00001e02f02c451189a709b9a952aaec",
          "previousStreams": 124595563,
          "dailyGain": 0,
          "yesterdayGain": 55109,
          "gainDifference": -55109,
          "formattedStreams": "124.6M",
          "formattedDailyGain": "0",
          "formattedGainDifference": "-55109"
        }
      ]
    },
    {
      "title": "Who (Remixes)",
      "type": "SINGLE",
      "image": "https://i.scdn.co/image/ab67616d00001e027f35adfbec3bb2bc8256802b",
      "streams": 2879019064,
      "dailyGain": 1512681,
      "songs": [
        {
          "title": "Who",
          "streams": 2485369526,
          "trackId": "1yqdD2ScjkqvaNBUzPQ4vR",
          "release": "Who (Remixes)",
          "releaseType": "SINGLE",
          "image": "https://i.scdn.co/image/ab67616d00001e027f35adfbec3bb2bc8256802b",
          "previousStreams": 2484005032,
          "dailyGain": 1364494,
          "yesterdayGain": 1351935,
          "gainDifference": 12559,
          "formattedStreams": "2.49B",
          "formattedDailyGain": "+1.4M",
          "formattedGainDifference": "+12.6K"
        },
        {
          "title": "Who (Rock Remix)",
          "streams": 77289983,
          "trackId": "2x9lpe6UIHNqLf8fB8qpb7",
          "release": "Who (Remixes)",
          "releaseType": "SINGLE",
          "image": "https://i.scdn.co/image/ab67616d00001e027f35adfbec3bb2bc8256802b",
          "previousStreams": 77248900,
          "dailyGain": 41083,
          "yesterdayGain": 49791,
          "gainDifference": -8708,
          "formattedStreams": "77.3M",
          "formattedDailyGain": "+41.1K",
          "formattedGainDifference": "-8708"
        },
        {
          "title": "Who (Acoustic Remix)",
          "streams": 75184510,
          "trackId": "2YKecnWyzkGEDTyNaKBG2H",
          "release": "Who (Remixes)",
          "releaseType": "SINGLE",
          "image": "https://i.scdn.co/image/ab67616d00001e027f35adfbec3bb2bc8256802b",
          "previousStreams": 75146779,
          "dailyGain": 37731,
          "yesterdayGain": 38548,
          "gainDifference": -817,
          "formattedStreams": "75.2M",
          "formattedDailyGain": "+37.7K",
          "formattedGainDifference": "-817"
        },
        {
          "title": "Who (Shibuyakei Remix)",
          "streams": 61831299,
          "trackId": "1PNdJibg1adHD1pTpYBfGc",
          "release": "Who (Remixes)",
          "releaseType": "SINGLE",
          "image": "https://i.scdn.co/image/ab67616d00001e027f35adfbec3bb2bc8256802b",
          "previousStreams": 61813116,
          "dailyGain": 18183,
          "yesterdayGain": 17868,
          "gainDifference": 315,
          "formattedStreams": "61.8M",
          "formattedDailyGain": "+18.2K",
          "formattedGainDifference": "+315"
        },
        {
          "title": "Who (Instrumental)",
          "streams": 60757962,
          "trackId": "6t7t37Bex3DV4ADqAwUmwa",
          "release": "Who (Remixes)",
          "releaseType": "SINGLE",
          "image": "https://i.scdn.co/image/ab67616d00001e027f35adfbec3bb2bc8256802b",
          "previousStreams": 60740980,
          "dailyGain": 16982,
          "yesterdayGain": 16303,
          "gainDifference": 679,
          "formattedStreams": "60.8M",
          "formattedDailyGain": "+17K",
          "formattedGainDifference": "+679"
        },
        {
          "title": "Who (Funky Remix)",
          "streams": 59424455,
          "trackId": "6E9BsGMop0G1jrpQNzugXv",
          "release": "Who (Remixes)",
          "releaseType": "SINGLE",
          "image": "https://i.scdn.co/image/ab67616d00001e027f35adfbec3bb2bc8256802b",
          "previousStreams": 59407564,
          "dailyGain": 16891,
          "yesterdayGain": 16589,
          "gainDifference": 302,
          "formattedStreams": "59.4M",
          "formattedDailyGain": "+16.9K",
          "formattedGainDifference": "+302"
        },
        {
          "title": "Who (Beautiful Mind Remix)",
          "streams": 59161329,
          "trackId": "1GDjQlek7EFZ3qTyySTSAF",
          "release": "Who (Remixes)",
          "releaseType": "SINGLE",
          "image": "https://i.scdn.co/image/ab67616d00001e027f35adfbec3bb2bc8256802b",
          "previousStreams": 59144012,
          "dailyGain": 17317,
          "yesterdayGain": 16166,
          "gainDifference": 1151,
          "formattedStreams": "59.2M",
          "formattedDailyGain": "+17.3K",
          "formattedGainDifference": "+1.2K"
        }
      ]
    },
    {
      "title": "FACE",
      "type": "EP",
      "image": "https://i.scdn.co/image/ab67616d00001e022b46078245d0120690eb560d",
      "streams": 2799330293,
      "dailyGain": 0,
      "songs": [
        {
          "title": "Like Crazy",
          "streams": 1467624698,
          "trackId": "3Ua0m0YmEjrMi9XErKcNiR",
          "release": "FACE",
          "releaseType": "EP",
          "image": "https://i.scdn.co/image/ab67616d00001e022b46078245d0120690eb560d",
          "previousStreams": 1467624698,
          "dailyGain": 0,
          "yesterdayGain": 234265,
          "gainDifference": -234265,
          "formattedStreams": "1.47B",
          "formattedDailyGain": "0",
          "formattedGainDifference": "-234265"
        },
        {
          "title": "Set Me Free Pt.2",
          "streams": 480206721,
          "trackId": "1fpj1CJPxY3YvN3AMAEYvt",
          "release": "FACE",
          "releaseType": "EP",
          "image": "https://i.scdn.co/image/ab67616d00001e022b46078245d0120690eb560d",
          "previousStreams": 480206721,
          "dailyGain": 0,
          "yesterdayGain": 134094,
          "gainDifference": -134094,
          "formattedStreams": "480.2M",
          "formattedDailyGain": "0",
          "formattedGainDifference": "-134094"
        },
        {
          "title": "Like Crazy (English Version)",
          "streams": 401144941,
          "trackId": "0u8rZGtXJrLtiSe34FPjGG",
          "release": "FACE",
          "releaseType": "EP",
          "image": "https://i.scdn.co/image/ab67616d00001e022b46078245d0120690eb560d",
          "previousStreams": 401144941,
          "dailyGain": 0,
          "yesterdayGain": 60823,
          "gainDifference": -60823,
          "formattedStreams": "401.1M",
          "formattedDailyGain": "0",
          "formattedGainDifference": "-60823"
        },
        {
          "title": "Face-off",
          "streams": 168354459,
          "trackId": "3OdIiWnYRHPYtC313Z0Bwy",
          "release": "FACE",
          "releaseType": "EP",
          "image": "https://i.scdn.co/image/ab67616d00001e022b46078245d0120690eb560d",
          "previousStreams": 168354459,
          "dailyGain": 0,
          "yesterdayGain": 58478,
          "gainDifference": -58478,
          "formattedStreams": "168.4M",
          "formattedDailyGain": "0",
          "formattedGainDifference": "-58478"
        },
        {
          "title": "Alone",
          "streams": 155368501,
          "trackId": "5Hfnps0jaWFpYg55WOPexG",
          "release": "FACE",
          "releaseType": "EP",
          "image": "https://i.scdn.co/image/ab67616d00001e022b46078245d0120690eb560d",
          "previousStreams": 155368501,
          "dailyGain": 0,
          "yesterdayGain": 41428,
          "gainDifference": -41428,
          "formattedStreams": "155.4M",
          "formattedDailyGain": "0",
          "formattedGainDifference": "-41428"
        },
        {
          "title": "Interlude : Dive",
          "streams": 126630973,
          "trackId": "2qg2jy3v50RwfV5FAqG3a2",
          "release": "FACE",
          "releaseType": "EP",
          "image": "https://i.scdn.co/image/ab67616d00001e022b46078245d0120690eb560d",
          "previousStreams": 126630973,
          "dailyGain": 0,
          "yesterdayGain": 19060,
          "gainDifference": -19060,
          "formattedStreams": "126.6M",
          "formattedDailyGain": "0",
          "formattedGainDifference": "-19060"
        }
      ]
    },
    {
      "title": "Like Crazy (Remixes)",
      "type": "EP",
      "image": "https://i.scdn.co/image/ab67616d00001e02f9638e7ed5b7d42e9c514195",
      "streams": 1968666414,
      "dailyGain": 289327,
      "songs": [
        {
          "title": "Like Crazy",
          "streams": 1467845149,
          "trackId": "58BWnoFDNaeM0vwA0K3fqb",
          "release": "Like Crazy (Remixes)",
          "releaseType": "EP",
          "image": "https://i.scdn.co/image/ab67616d00001e02f9638e7ed5b7d42e9c514195",
          "previousStreams": 1467624698,
          "dailyGain": 220451,
          "yesterdayGain": 234265,
          "gainDifference": -13814,
          "formattedStreams": "1.47B",
          "formattedDailyGain": "+220.5K",
          "formattedGainDifference": "-13814"
        },
        {
          "title": "Like Crazy (English Version)",
          "streams": 401198395,
          "trackId": "6EY9e6LyPWmL8hUS5E1P0h",
          "release": "Like Crazy (Remixes)",
          "releaseType": "EP",
          "image": "https://i.scdn.co/image/ab67616d00001e02f9638e7ed5b7d42e9c514195",
          "previousStreams": 401144941,
          "dailyGain": 53454,
          "yesterdayGain": 60823,
          "gainDifference": -7369,
          "formattedStreams": "401.2M",
          "formattedDailyGain": "+53.5K",
          "formattedGainDifference": "-7369"
        },
        {
          "title": "Like Crazy (Deep House Remix)",
          "streams": 37578214,
          "trackId": "6D90VTeGEWYX5AkAtjHZh1",
          "release": "Like Crazy (Remixes)",
          "releaseType": "EP",
          "image": "https://i.scdn.co/image/ab67616d00001e02f9638e7ed5b7d42e9c514195",
          "previousStreams": 37572502,
          "dailyGain": 5712,
          "yesterdayGain": 6479,
          "gainDifference": -767,
          "formattedStreams": "37.6M",
          "formattedDailyGain": "+5.7K",
          "formattedGainDifference": "-767"
        },
        {
          "title": "Like Crazy (UK Garage Remix)",
          "streams": 35749684,
          "trackId": "5tDxLjAnkojfnXnjOk6mvh",
          "release": "Like Crazy (Remixes)",
          "releaseType": "EP",
          "image": "https://i.scdn.co/image/ab67616d00001e02f9638e7ed5b7d42e9c514195",
          "previousStreams": 35744572,
          "dailyGain": 5112,
          "yesterdayGain": 5756,
          "gainDifference": -644,
          "formattedStreams": "35.7M",
          "formattedDailyGain": "+5.1K",
          "formattedGainDifference": "-644"
        },
        {
          "title": "Like Crazy (Instrumental)",
          "streams": 26294972,
          "trackId": "0cxhv3PpIkmREXqobuB0zG",
          "release": "Like Crazy (Remixes)",
          "releaseType": "EP",
          "image": "https://i.scdn.co/image/ab67616d00001e02f9638e7ed5b7d42e9c514195",
          "previousStreams": 26290374,
          "dailyGain": 4598,
          "yesterdayGain": 5206,
          "gainDifference": -608,
          "formattedStreams": "26.3M",
          "formattedDailyGain": "+4.6K",
          "formattedGainDifference": "-608"
        }
      ]
    },
    {
      "title": "Angel Pt. 1 (feat. Jimin of BTS, JVKE & Muni Long) (FAST X Soundtrack)",
      "type": "SINGLE",
      "image": "https://i.scdn.co/image/ab67616d00001e02be4afaf12bdbcfd17d95f22b",
      "streams": 814868537,
      "dailyGain": 64152,
      "songs": [
        {
          "title": "Angel Pt. 1 (feat. Jimin of BTS, JVKE & Muni Long)",
          "streams": 246974291,
          "trackId": "4TZYldxfZlV3hKtZGl8kRb",
          "release": "Angel Pt. 1 (feat. Jimin of BTS, JVKE & Muni Long) (FAST X Soundtrack)",
          "releaseType": "SINGLE",
          "image": "https://i.scdn.co/image/ab67616d00001e02be4afaf12bdbcfd17d95f22b",
          "previousStreams": 246943039,
          "dailyGain": 31252,
          "yesterdayGain": 35760,
          "gainDifference": -4508,
          "formattedStreams": "247M",
          "formattedDailyGain": "+31.3K",
          "formattedGainDifference": "-4508"
        },
        {
          "title": "Angel Pt. 1 (feat. Jimin of BTS, JVKE & Muni Long)",
          "streams": 246943039,
          "trackId": "2tC8dLnjkNFMGOqaYMSjcp",
          "release": "Angel Pt. 1 (feat. Jimin of BTS, JVKE & Muni Long) (FAST X Soundtrack)",
          "releaseType": "SINGLE",
          "image": "https://i.scdn.co/image/ab67616d00001e0221ba737cb75af968200cf4bc",
          "previousStreams": 246943039,
          "dailyGain": 0,
          "yesterdayGain": 35760,
          "gainDifference": -35760,
          "formattedStreams": "246.9M",
          "formattedDailyGain": "0",
          "formattedGainDifference": "-35760"
        },
        {
          "title": "Angel Pt. 2 (feat. Jimin of BTS, Charlie Puth and Muni Long)",
          "streams": 132991392,
          "trackId": "2yjeXq5ahx6UUg2rHaUe6X",
          "release": "Angel Pt. 1 (feat. Jimin of BTS, JVKE & Muni Long) (FAST X Soundtrack)",
          "releaseType": "SINGLE",
          "image": "https://i.scdn.co/image/ab67616d00001e02be4afaf12bdbcfd17d95f22b",
          "previousStreams": 132958492,
          "dailyGain": 32900,
          "yesterdayGain": 38457,
          "gainDifference": -5557,
          "formattedStreams": "133M",
          "formattedDailyGain": "+32.9K",
          "formattedGainDifference": "-5557"
        },
        {
          "title": "Angel Pt. 2 (feat. Jimin of BTS, Charlie Puth and Muni Long)",
          "streams": 132958492,
          "trackId": "7miSbL2vUkrkkrRZf1jcmq",
          "release": "Angel Pt. 1 (feat. Jimin of BTS, JVKE & Muni Long) (FAST X Soundtrack)",
          "releaseType": "SINGLE",
          "image": "https://i.scdn.co/image/ab67616d00001e0221ba737cb75af968200cf4bc",
          "previousStreams": 132958492,
          "dailyGain": 0,
          "yesterdayGain": 38457,
          "gainDifference": -38457,
          "formattedStreams": "133M",
          "formattedDailyGain": "0",
          "formattedGainDifference": "-38457"
        },
        {
          "title": "Angel Pt. 1 (feat. Jimin of BTS, JVKE & Muni Long) - Trailer Version",
          "streams": 55001323,
          "trackId": "2rgCR1PPHPGJBppdBOqor0",
          "release": "Angel Pt. 1 (feat. Jimin of BTS, JVKE & Muni Long) (FAST X Soundtrack)",
          "releaseType": "SINGLE",
          "image": "https://i.scdn.co/image/ab67616d00001e0221ba737cb75af968200cf4bc",
          "previousStreams": 55001323,
          "dailyGain": 0,
          "yesterdayGain": 8549,
          "gainDifference": -8549,
          "formattedStreams": "55M",
          "formattedDailyGain": "0",
          "formattedGainDifference": "-8549"
        }
      ]
    },
    {
      "title": "Set Me Free Pt.2",
      "type": "SINGLE",
      "image": "https://i.scdn.co/image/ab67616d00001e024f4ec2c2a865569bd4a067a4",
      "streams": 480206721,
      "dailyGain": 0,
      "songs": [
        {
          "title": "Set Me Free Pt.2",
          "streams": 480206721,
          "trackId": "59hBR0BCtJsfIbV9VzCVAp",
          "release": "Set Me Free Pt.2",
          "releaseType": "SINGLE",
          "image": "https://i.scdn.co/image/ab67616d00001e024f4ec2c2a865569bd4a067a4",
          "previousStreams": 480206721,
          "dailyGain": 0,
          "yesterdayGain": 134094,
          "gainDifference": -134094,
          "formattedStreams": "480.2M",
          "formattedDailyGain": "0",
          "formattedGainDifference": "-134094"
        }
      ]
    },
    {
      "title": "Be Mine (English Version)",
      "type": "SINGLE",
      "image": "https://i.scdn.co/image/ab67616d00001e0219655636129722b4bd720dbc",
      "streams": 396748597,
      "dailyGain": 0,
      "songs": [
        {
          "title": "Be Mine (English Version)",
          "streams": 396748597,
          "trackId": "4DairgmwgyfmFHm0e7kRPL",
          "release": "Be Mine (English Version)",
          "releaseType": "SINGLE",
          "image": "https://i.scdn.co/image/ab67616d00001e0219655636129722b4bd720dbc",
          "previousStreams": 396748597,
          "dailyGain": 0,
          "yesterdayGain": 267524,
          "gainDifference": -267524,
          "formattedStreams": "396.7M",
          "formattedDailyGain": "0",
          "formattedGainDifference": "-267524"
        }
      ]
    },
    {
      "title": "Angel Anniversary Edition (feat. Muni Long, JVKE, NLE Choppa)",
      "type": "SINGLE",
      "image": "https://i.scdn.co/image/ab67616d00001e0232107dc4737279267c8e00f5",
      "streams": 391183501,
      "dailyGain": 66160,
      "songs": [
        {
          "title": "Angel Pt. 1 (feat. Kodak Black, NLE Choppa, Jimin of BTS, JVKE & Muni Long)",
          "streams": 246974291,
          "trackId": "1FEGCMAqh9wzjVM7bPBORE",
          "release": "Angel Anniversary Edition (feat. Muni Long, JVKE, NLE Choppa)",
          "releaseType": "SINGLE",
          "image": "https://i.scdn.co/image/ab67616d00001e0232107dc4737279267c8e00f5",
          "previousStreams": 246943039,
          "dailyGain": 31252,
          "yesterdayGain": 35760,
          "gainDifference": -4508,
          "formattedStreams": "247M",
          "formattedDailyGain": "+31.3K",
          "formattedGainDifference": "-4508"
        },
        {
          "title": "Angel Pt. 2 (feat. Jimin of BTS & JVKE feat. Charlie Puth & Muni Long)",
          "streams": 132991392,
          "trackId": "3gSobY1JXFJn6wh1ON35ni",
          "release": "Angel Anniversary Edition (feat. Muni Long, JVKE, NLE Choppa)",
          "releaseType": "SINGLE",
          "image": "https://i.scdn.co/image/ab67616d00001e0232107dc4737279267c8e00f5",
          "previousStreams": 132958492,
          "dailyGain": 32900,
          "yesterdayGain": 38457,
          "gainDifference": -5557,
          "formattedStreams": "133M",
          "formattedDailyGain": "+32.9K",
          "formattedGainDifference": "-5557"
        },
        {
          "title": "Angel (feat. Muni Long, JVKE, NLE Choppa) (Anniversary Edition)",
          "streams": 5609913,
          "trackId": "2PMEMxJCxOz0RGT0mQXXZq",
          "release": "Angel Anniversary Edition (feat. Muni Long, JVKE, NLE Choppa)",
          "releaseType": "SINGLE",
          "image": "https://i.scdn.co/image/ab67616d00001e0232107dc4737279267c8e00f5",
          "previousStreams": 5607905,
          "dailyGain": 2008,
          "yesterdayGain": 3157,
          "gainDifference": -1149,
          "formattedStreams": "5.6M",
          "formattedDailyGain": "+2K",
          "formattedGainDifference": "-1149"
        },
        {
          "title": "Angel (feat. Muni Long, JVKE, NLE Choppa) (Anniversary Edition)",
          "streams": 5607905,
          "trackId": "1XE3rehhUySx3O1fALkswV",
          "release": "Angel Anniversary Edition (feat. Muni Long, JVKE, NLE Choppa)",
          "releaseType": "SINGLE",
          "image": "https://i.scdn.co/image/ab67616d00001e025cae2e3d2932cd9283cc53ff",
          "previousStreams": 5607905,
          "dailyGain": 0,
          "yesterdayGain": 3157,
          "gainDifference": -3157,
          "formattedStreams": "5.6M",
          "formattedDailyGain": "0",
          "formattedGainDifference": "-3157"
        }
      ]
    },
    {
      "title": "Angel Pt. 1 (feat. Jimin of BTS, JVKE & Muni Long) [Trailer Version]",
      "type": "SINGLE",
      "image": "https://i.scdn.co/image/ab67616d00001e02445afb6341d2685b959251cc",
      "streams": 356990603,
      "dailyGain": 44918,
      "songs": [
        {
          "title": "Angel Pt. 1 (feat. Jimin of BTS, JVKE & Muni Long)",
          "streams": 246974291,
          "trackId": "1vvcEHQdaUTvWt0EIUYcFK",
          "release": "Angel Pt. 1 (feat. Jimin of BTS, JVKE & Muni Long) [Trailer Version]",
          "releaseType": "SINGLE",
          "image": "https://i.scdn.co/image/ab67616d00001e02445afb6341d2685b959251cc",
          "previousStreams": 246943039,
          "dailyGain": 31252,
          "yesterdayGain": 35760,
          "gainDifference": -4508,
          "formattedStreams": "247M",
          "formattedDailyGain": "+31.3K",
          "formattedGainDifference": "-4508"
        },
        {
          "title": "Angel Pt. 1 (feat. Jimin of BTS, JVKE & Muni Long) - Trailer Version",
          "streams": 55008156,
          "trackId": "2GhOHZynysGm5B8R6iCihi",
          "release": "Angel Pt. 1 (feat. Jimin of BTS, JVKE & Muni Long) [Trailer Version]",
          "releaseType": "SINGLE",
          "image": "https://i.scdn.co/image/ab67616d00001e02445afb6341d2685b959251cc",
          "previousStreams": 55001323,
          "dailyGain": 6833,
          "yesterdayGain": 8549,
          "gainDifference": -1716,
          "formattedStreams": "55M",
          "formattedDailyGain": "+6.8K",
          "formattedGainDifference": "-1716"
        },
        {
          "title": "Angel Pt. 1 (feat. Jimin of BTS, JVKE & Muni Long) - Trailer Version",
          "streams": 55008156,
          "trackId": "5qyjy0xfsHNzWxvXkHVB85",
          "release": "Angel Pt. 1 (feat. Jimin of BTS, JVKE & Muni Long) [Trailer Version]",
          "releaseType": "SINGLE",
          "image": "https://i.scdn.co/image/ab67616d00001e02146ea147ce8c185e71b3b84e",
          "previousStreams": 55001323,
          "dailyGain": 6833,
          "yesterdayGain": 8549,
          "gainDifference": -1716,
          "formattedStreams": "55M",
          "formattedDailyGain": "+6.8K",
          "formattedGainDifference": "-1716"
        }
      ]
    },
    {
      "title": "Our Blues, Pt. 4 (Original Television Soundtrack)",
      "type": "SINGLE",
      "image": "https://i.scdn.co/image/ab67616d00001e02d90bd8b97e49216c00e55d18",
      "streams": 348146223,
      "dailyGain": 41620,
      "songs": [
        {
          "title": "With you",
          "streams": 326258417,
          "trackId": "2gzhQaCTeNgxpeB2TPllyY",
          "release": "Our Blues, Pt. 4 (Original Television Soundtrack)",
          "releaseType": "SINGLE",
          "image": "https://i.scdn.co/image/ab67616d00001e02d90bd8b97e49216c00e55d18",
          "previousStreams": 326217915,
          "dailyGain": 40502,
          "yesterdayGain": 44291,
          "gainDifference": -3789,
          "formattedStreams": "326.3M",
          "formattedDailyGain": "+40.5K",
          "formattedGainDifference": "-3789"
        },
        {
          "title": "With you - Instrumental",
          "streams": 21887806,
          "trackId": "7M30L99pePlQ3wh8IxVUsD",
          "release": "Our Blues, Pt. 4 (Original Television Soundtrack)",
          "releaseType": "SINGLE",
          "image": "https://i.scdn.co/image/ab67616d00001e02d90bd8b97e49216c00e55d18",
          "previousStreams": 21886688,
          "dailyGain": 1118,
          "yesterdayGain": 1535,
          "gainDifference": -417,
          "formattedStreams": "21.9M",
          "formattedDailyGain": "+1.1K",
          "formattedGainDifference": "-417"
        }
      ]
    },
    {
      "title": "Closer Than This",
      "type": "SINGLE",
      "image": "https://i.scdn.co/image/ab67616d00001e02e3dbc03f538633dbb40adf37",
      "streams": 333455036,
      "dailyGain": 85955,
      "songs": [
        {
          "title": "Closer Than This",
          "streams": 333455036,
          "trackId": "3k6q0O9JnO2GhvD6C8fs20",
          "release": "Closer Than This",
          "releaseType": "SINGLE",
          "image": "https://i.scdn.co/image/ab67616d00001e02e3dbc03f538633dbb40adf37",
          "previousStreams": 333369081,
          "dailyGain": 85955,
          "yesterdayGain": 92885,
          "gainDifference": -6930,
          "formattedStreams": "333.5M",
          "formattedDailyGain": "+86K",
          "formattedGainDifference": "-6930"
        }
      ]
    },
    {
      "title": "VIBE (feat. Jimin of BTS)",
      "type": "SINGLE",
      "image": "https://i.scdn.co/image/ab67616d00001e02278d6cf14513bd97cb580fe7",
      "streams": 276758704,
      "dailyGain": 47038,
      "songs": [
        {
          "title": "VIBE (feat. Jimin of BTS)",
          "streams": 276758704,
          "trackId": "14XLUySagFhP9KoqOTg5ka",
          "release": "VIBE (feat. Jimin of BTS)",
          "releaseType": "SINGLE",
          "image": "https://i.scdn.co/image/ab67616d00001e02278d6cf14513bd97cb580fe7",
          "previousStreams": 276711666,
          "dailyGain": 47038,
          "yesterdayGain": 61310,
          "gainDifference": -14272,
          "formattedStreams": "276.8M",
          "formattedDailyGain": "+47K",
          "formattedGainDifference": "-14272"
        }
      ]
    },
    {
      "title": "Smeraldo Garden Marching Band (feat. Loco)",
      "type": "SINGLE",
      "image": "https://i.scdn.co/image/ab67616d00001e0238881a83135ef5b4ace418ba",
      "streams": 275372483,
      "dailyGain": 81052,
      "songs": [
        {
          "title": "Smeraldo Garden Marching Band (feat. Loco)",
          "streams": 275372483,
          "trackId": "1kPhV0KQui1phEpjnWIqUN",
          "release": "Smeraldo Garden Marching Band (feat. Loco)",
          "releaseType": "SINGLE",
          "image": "https://i.scdn.co/image/ab67616d00001e0238881a83135ef5b4ace418ba",
          "previousStreams": 275291431,
          "dailyGain": 81052,
          "yesterdayGain": 85444,
          "gainDifference": -4392,
          "formattedStreams": "275.4M",
          "formattedDailyGain": "+81.1K",
          "formattedGainDifference": "-4392"
        }
      ]
    },
    {
      "title": "Angel Pt. 1 (feat. Jimin of BTS, JVKE & Muni Long / FAST X Soundtrack)",
      "type": "SINGLE",
      "image": "https://i.scdn.co/image/ab67616d00001e02beac2a5a6392353b63e5ef15",
      "streams": 246943039,
      "dailyGain": 0,
      "songs": [
        {
          "title": "Angel Pt. 1 (feat. Jimin of BTS, JVKE & Muni Long)",
          "streams": 246943039,
          "trackId": "4g1Ant3Me43Cm5Lx91bV8e",
          "release": "Angel Pt. 1 (feat. Jimin of BTS, JVKE & Muni Long / FAST X Soundtrack)",
          "releaseType": "SINGLE",
          "image": "https://i.scdn.co/image/ab67616d00001e02beac2a5a6392353b63e5ef15",
          "previousStreams": 246943039,
          "dailyGain": 0,
          "yesterdayGain": 35760,
          "gainDifference": -35760,
          "formattedStreams": "246.9M",
          "formattedDailyGain": "0",
          "formattedGainDifference": "-35760"
        }
      ]
    },
    {
      "title": "Promise",
      "type": "SINGLE",
      "image": "https://i.scdn.co/image/ab67616d00001e0221d21c44fa7a2495c37ce088",
      "streams": 149123433,
      "dailyGain": 0,
      "songs": [
        {
          "title": "Promise",
          "streams": 149123433,
          "trackId": "2RUcwyW74Sv4VracHFrKdh",
          "release": "Promise",
          "releaseType": "SINGLE",
          "image": "https://i.scdn.co/image/ab67616d00001e0221d21c44fa7a2495c37ce088",
          "previousStreams": 149123433,
          "dailyGain": 0,
          "yesterdayGain": 79491,
          "gainDifference": -79491,
          "formattedStreams": "149.1M",
          "formattedDailyGain": "0",
          "formattedGainDifference": "-79491"
        }
      ]
    },
    {
      "title": "Angel Pt. 2 (Acoustic Version)",
      "type": "SINGLE",
      "image": "https://i.scdn.co/image/ab67616d00001e0279f6a219e637ccf7305d622d",
      "streams": 145171989,
      "dailyGain": 0,
      "songs": [
        {
          "title": "Angel Pt. 2",
          "streams": 132958492,
          "trackId": "2q6GfDEbNUwJENX6EZLK4Q",
          "release": "Angel Pt. 2 (Acoustic Version)",
          "releaseType": "SINGLE",
          "image": "https://i.scdn.co/image/ab67616d00001e0279f6a219e637ccf7305d622d",
          "previousStreams": 132958492,
          "dailyGain": 0,
          "yesterdayGain": 38457,
          "gainDifference": -38457,
          "formattedStreams": "133M",
          "formattedDailyGain": "0",
          "formattedGainDifference": "-38457"
        },
        {
          "title": "Angel Pt. 2 - Acoustic Version",
          "streams": 8059597,
          "trackId": "46rplB2GaD79JaBn94qfqi",
          "release": "Angel Pt. 2 (Acoustic Version)",
          "releaseType": "SINGLE",
          "image": "https://i.scdn.co/image/ab67616d00001e0279f6a219e637ccf7305d622d",
          "previousStreams": 8059597,
          "dailyGain": 0,
          "yesterdayGain": 3014,
          "gainDifference": -3014,
          "formattedStreams": "8.1M",
          "formattedDailyGain": "0",
          "formattedGainDifference": "-3014"
        },
        {
          "title": "Angel Pt. 2 - Sped Up",
          "streams": 4153900,
          "trackId": "6aB2aRNg9gTj6XMQkW0yQk",
          "release": "Angel Pt. 2 (Acoustic Version)",
          "releaseType": "SINGLE",
          "image": "https://i.scdn.co/image/ab67616d00001e0279f6a219e637ccf7305d622d",
          "previousStreams": 4153900,
          "dailyGain": 0,
          "yesterdayGain": 2282,
          "gainDifference": -2282,
          "formattedStreams": "4.2M",
          "formattedDailyGain": "0",
          "formattedGainDifference": "-2282"
        }
      ]
    },
    {
      "title": "Angel Pt. 2 (feat. Jimin of BTS, Charlie Puth & Muni Long) (Sped Up) [FAST X Soundtrack]",
      "type": "SINGLE",
      "image": "https://i.scdn.co/image/ab67616d00001e02deaa79daadaf2236d1ac1003",
      "streams": 137112392,
      "dailyGain": 0,
      "songs": [
        {
          "title": "Angel Pt. 2 (feat. Jimin of BTS, Charlie Puth and Muni Long)",
          "streams": 132958492,
          "trackId": "7lVAWCO7Z6n1bQvLGe2EW3",
          "release": "Angel Pt. 2 (feat. Jimin of BTS, Charlie Puth & Muni Long) (Sped Up) [FAST X Soundtrack]",
          "releaseType": "SINGLE",
          "image": "https://i.scdn.co/image/ab67616d00001e02deaa79daadaf2236d1ac1003",
          "previousStreams": 132958492,
          "dailyGain": 0,
          "yesterdayGain": 38457,
          "gainDifference": -38457,
          "formattedStreams": "133M",
          "formattedDailyGain": "0",
          "formattedGainDifference": "-38457"
        },
        {
          "title": "Angel Pt. 2 (feat. Jimin of BTS, Charlie Puth & Muni Long) (Sped Up)",
          "streams": 4153900,
          "trackId": "4rrGx1CX8RwQMl2ufnQzUA",
          "release": "Angel Pt. 2 (feat. Jimin of BTS, Charlie Puth & Muni Long) (Sped Up) [FAST X Soundtrack]",
          "releaseType": "SINGLE",
          "image": "https://i.scdn.co/image/ab67616d00001e02deaa79daadaf2236d1ac1003",
          "previousStreams": 4153900,
          "dailyGain": 0,
          "yesterdayGain": 2282,
          "gainDifference": -2282,
          "formattedStreams": "4.2M",
          "formattedDailyGain": "0",
          "formattedGainDifference": "-2282"
        }
      ]
    },
    {
      "title": "Angel Pt. 2 (feat. Jimin of BTS, Charlie Puth and Muni Long / FAST X Soundtrack)",
      "type": "SINGLE",
      "image": "https://i.scdn.co/image/ab67616d00001e023af4efcbc640cf0cb0888d63",
      "streams": 132991392,
      "dailyGain": 32900,
      "songs": [
        {
          "title": "Angel Pt. 2 (feat. Jimin of BTS, Charlie Puth and Muni Long / FAST X Soundtrack)",
          "streams": 132991392,
          "trackId": "0ApadYqa3GRQkJJ3E7pQDJ",
          "release": "Angel Pt. 2 (feat. Jimin of BTS, Charlie Puth and Muni Long / FAST X Soundtrack)",
          "releaseType": "SINGLE",
          "image": "https://i.scdn.co/image/ab67616d00001e023af4efcbc640cf0cb0888d63",
          "previousStreams": 132958492,
          "dailyGain": 32900,
          "yesterdayGain": 38457,
          "gainDifference": -5557,
          "formattedStreams": "133M",
          "formattedDailyGain": "+32.9K",
          "formattedGainDifference": "-5557"
        }
      ]
    },
    {
      "title": "Christmas Love",
      "type": "SINGLE",
      "image": "https://i.scdn.co/image/ab67616d00001e026102fbfee73db153a32d02ab",
      "streams": 49728144,
      "dailyGain": 11199,
      "songs": [
        {
          "title": "Christmas Love",
          "streams": 49728144,
          "trackId": "5oaQsszgxYAdABuXoWEOUe",
          "release": "Christmas Love",
          "releaseType": "SINGLE",
          "image": "https://i.scdn.co/image/ab67616d00001e026102fbfee73db153a32d02ab",
          "previousStreams": 49716945,
          "dailyGain": 11199,
          "yesterdayGain": 12018,
          "gainDifference": -819,
          "formattedStreams": "49.7M",
          "formattedDailyGain": "+11.2K",
          "formattedGainDifference": "-819"
        }
      ]
    }
  ]
}